Workbook
Name Slicer_Buyer_segment: #N/A
Name Slicer_Country_origin: #N/A
Name Slicer_Order_Year: #N/A

Sheet Guide
A1: Ketentuan
A2: 1 | B2: Selesaikanlah tahapan berikut ini
A3: - | B3: Buatlah Order Code dengan format sebagai berikut: ORD-(Origin Code)-(Segment Code)-(Order date)
A4: - | B4: Format dari Order date pada Order Code adalah yyyymmdd
A5: - | B5: Contoh | C5: : ORD-GER-GOV-20141201
A6: 2 | B6: Ekstrak informasi Order details menjadi kolom-kolom individu
A7: 3 | B7: Lakukan pemrosesan data dengan melengkapi informasi pada sheet Order raw (lookup dan perhitungan) untuk memperoleh informasi berikut:
A8: - | B8: Total price | C8: : Selling price x qty
A9: - | B9: Revenue | C9: : Total price - discount
A10: - | B10: Gross profit | C10: : Revenue - Manufacturing cost
A11: 4 | B11: Lakukan analisa terhadap data perjualan dari beberapa tahun tersebut
A12: 5 | B12: Lakukan analisa lanjutan untuk melihat bagaimana performa tahunan keuangan perusahaan secara keseluruhan dengan mencari nilai berikut secara garis besar
A13: - | B13: Operating profit | C13: : Gross profit - G&A cost - Handling cost
A14: - | B14: Net profit | C14: : Operating profit - tax
A15: 6 | B15: Dari analisa yang dilakukan, tampilan insight dalam bentuk dashboard dengan minimal terdapat 4 chart dan 1 slicer (gunakan pivot table agar lebih mudah)
A16: 7 | B16: Sajikan data dengan baik dan lakukan presentasi terhadap hasil dari analisa yang dilakukan
A17: 8 | B17: Anda bebas menambahkan parameter lain jika memang diperlukan untuk memperoleh hasil analisa yang diinginkan
A19: Informasi Tambahan
B21: Nama negara | C21: Kode negara
B22: Canada | C22: CND
B23: Germany | C23: GER
B24: France | C24: FRA
B25: Mexico | C25: MXC
B26: United States of America | C26: USA
B28: Nama segmen | C28: Kode segmen
B29: Government | C29: GOV
B30: Midmarket | C30: MDM
B31: Channel Partners | C31: CPR
B32: Enterprise | C32: ENT
B33: Small Business | C33: SMB
A35: Definisi kolom
B37: Nama kolom | C37: Keterangan
B38: Order ID | C38: Nomor order
B39: Order details | C39: Informasi order
B40: Country origin | C40: Negara asal pembeli
B41: Buyer segment | C41: Jenis segmen pembeli
B42: Product name | C42: Nama produk
B43: Qty sold | C43: Jumlah barang terjual
B44: Discount % | C44: Besar diskon yang diberikan
B45: Order date | C45: Tanggal pesanan/order

Sheet Order raw
A1: Order ID | B1: Order details | C1: Country origin | D1: Buyer segment | E1: Product name | F1: Qty sold | G1: Discount % | H1: Order date | I1: Selling Price | J1: Total Price | K1: Revenue | L1: Gross Profit | M1: Order Year | N1: Discount Tier | O1: Column1
A2: ="ORD"&"-"&_xlfn.XLOOKUP(C2,Guide!$B$22:$B$26,Guide!$C$22:$C$26)&"-"&_xlfn.XLOOKUP(D2,Guide!$B$29:$B$33,Guide!$C$29:$C$33)&"-"&TEXT(H2,"yyyymmdd") -> ORD-FRA-MDM-20130901 | B2: {"type": "buyerDetails", "info": ["origin": "France", "segment": "Midmarket", "date": "1", "month": "9", "year": "2013", "units": "549"]} | C2: France | D2: Midmarket | E2: Paseo | F2: 549 | G2: 0 | H2: =DATE(VALUE(_xlfn.TEXTBEFORE(_xlfn.TEXTAFTER(B2,"""year"": """),"""")),VALUE(_xlfn.TEXTBEFORE(_xlfn.TEXTAFTER(B2,"""month"": """),"""")),VALUE(_xlfn.TEXTBEFORE(_xlfn.TEXTAFTER(B2,"""date"": """),"""")) ) -> 41518 | I2: =_xlfn.XLOOKUP(E2,Product!$A$2:$A$7,Product!$C$2:$C$7) -> 20 | J2: =I2*F2 -> 10980 | K2: =J2*(1-IF(G2="-",0,G2)) -> 10980 | L2: =K2-(_xlfn.XLOOKUP(E2,Product!$A$2:$A$7,Product!$B$2:$B$7)*F2) -> 5490 | M2: =YEAR(Table1[[#This Row],[Order date]]) -> 2013 | N2: {=_xlfn.IFS(G2=0,"No Discount", ROUND(G2*100,0)<=4,"Low", ROUND(G2*100,0)<=9,"Medium", ROUND(G2*100,0)<=15,"High")} -> No Discount | O2: =TEXT(Table1[[#This Row],[Order date]],"mmmm") -> September
A3: ="ORD"&"-"&_xlfn.XLOOKUP(C3,Guide!$B$22:$B$26,Guide!$C$22:$C$26)&"-"&_xlfn.XLOOKUP(D3,Guide!$B$29:$B$33,Guide!$C$29:$C$33)&"-"&TEXT(H3,"yyyymmdd") -> ORD-MXC-SMB-20130901 | B3: {"type": "buyerDetails", "info": ["origin": "Mexico", "segment": "Small Business", "date": "1", "month": "9", "year": "2013", "units": "788"]} | C3: Mexico | D3: Small Business | E3: Paseo | F3: 788 | G3: 0 | H3: =DATE(VALUE(_xlfn.TEXTBEFORE(_xlfn.TEXTAFTER(B3,"""year"": """),"""")),VALUE(_xlfn.TEXTBEFORE(_xlfn.TEXTAFTER(B3,"""month"": """),"""")),VALUE(_xlfn.TEXTBEFORE(_xlfn.TEXTAFTER(B3,"""date"": """),"""")) ) -> 41518 | I3: =_xlfn.XLOOKUP(E3,Product!$A$2:$A$7,Product!$C$2:$C$7) -> 20 | J3: =I3*F3 -> 15760 | K3: =J3*(1-IF(G3="-",0,G3)) -> 15760 | L3: =K3-(_xlfn.XLOOKUP(E3,Product!$A$2:$A$7,Product!$B$2:$B$7)*F3) -> 7880 | M3: =YEAR(Table1[[#This Row],[Order date]]) -> 2013 | N3: {=_xlfn.IFS(G3=0,"No Discount", ROUND(G3*100,0)<=4,"Low", ROUND(G3*100,0)<=9,"Medium", ROUND(G3*100,0)<=15,"High")} -> No Discount | O3: =TEXT(Table1[[#This Row],[Order date]],"mmmm") -> September
A4: ="ORD"&"-"&_xlfn.XLOOKUP(C4,Guide!$B$22:$B$26,Guide!$C$22:$C$26)&"-"&_xlfn.XLOOKUP(D4,Guide!$B$29:$B$33,Guide!$C$29:$C$33)&"-"&TEXT(H4,"yyyymmdd") -> ORD-FRA-GOV-20130901 | B4: {"type": "buyerDetails", "info": ["origin": "France", "segment": "Government", "date": "1", "month": "9", "year": "2013", "units": "1527"]} | C4: France | D4: Government | E4: VTT | F4: 1527 | G4: 0 | H4: =DATE(VALUE(_xlfn.TEXTBEFORE(_xlfn.TEXTAFTER(B4,"""year"": """),"""")),VALUE(_xlfn.TEXTBEFORE(_xlfn.TEXTAFTER(B4,"""month"": """),"""")),VALUE(_xlfn.TEXTBEFORE(_xlfn.TEXTAFTER(B4,"""date"": """),"""")) ) -> 41518 | I4: =_xlfn.XLOOKUP(E4,Product!$A$2:$A$7,Product!$C$2:$C$7) -> 300 | J4: =I4*F4 -> 458100 | K4: =J4*(1-IF(G4="-",0,G4)) -> 458100 | L4: =K4-(_xlfn.XLOOKUP(E4,Product!$A$2:$A$7,Product!$B$2:$B$7)*F4) -> 76350 | M4: =YEAR(Table1[[#This Row],[Order date]]) -> 2013 | N4: {=_xlfn.IFS(G4=0,"No Discount", ROUND(G4*100,0)<=4,"Low", ROUND(G4*100,0)<=9,"Medium", ROUND(G4*100,0)<=15,"High")} -> No Discount | O4: =TEXT(Table1[[#This Row],[Order date]],"mmmm") -> September
A5: ="ORD"&"-"&_xlfn.XLOOKUP(C5,Guide!$B$22:$B$26,Guide!$C$22:$C$26)&"-"&_xlfn.XLOOKUP(D5,Guide!$B$29:$B$33,Guide!$C$29:$C$33)&"-"&TEXT(H5,"yyyymmdd") -> ORD-USA-ENT-20130901 | B5: {"type": "buyerDetails", "info": ["origin": "United States of America", "segment": "Enterprise", "date": "1", "month": "9", "year": "2013", "units": "330"]} | C5: United States of America | D5: Enterprise | E5: Carretera | F5: 330 | G5: 0.01 | H5: =DATE(VALUE(_xlfn.TEXTBEFORE(_xlfn.TEXTAFTER(B5,"""year"": """),"""")),VALUE(_xlfn.TEXTBEFORE(_xlfn.TEXTAFTER(B5,"""month"": """),"""")),VALUE(_xlfn.TEXTBEFORE(_xlfn.TEXTAFTER(B5,"""date"": """),"""")) ) -> 41518 | I5: =_xlfn.XLOOKUP(E5,Product!$A$2:$A$7,Product!$C$2:$C$7) -> 20 | J5: =I5*F5 -> 6600 | K5: =J5*(1-IF(G5="-",0,G5)) -> 6534 | L5: =K5-(_xlfn.XLOOKUP(E5,Product!$A$2:$A$7,Product!$B$2:$B$7)*F5) -> 5544 | M5: =YEAR(Table1[[#This Row],[Order date]]) -> 2013 | N5: {=_xlfn.IFS(G5=0,"No Discount", ROUND(G5*100,0)<=4,"Low", ROUND(G5*100,0)<=9,"Medium", ROUND(G5*100,0)<=15,"High")} -> Low | O5: =TEXT(Table1[[#This Row],[Order date]],"mmmm") -> September
A6: ="ORD"&"-"&_xlfn.XLOOKUP(C6,Guide!$B$22:$B$26,Guide!$C$22:$C$26)&"-"&_xlfn.XLOOKUP(D6,Guide!$B$29:$B$33,Guide!$C$29:$C$33)&"-"&TEXT(H6,"yyyymmdd") -> ORD-USA-SMB-20130901 | B6: {"type": "buyerDetails", "info": ["origin": "United States of America", "segment": "Small Business", "date": "1", "month": "9", "year": "2013", "units": "2498"]} | C6: United States of America | D6: Small Business | E6: Montana | F6: 2498 | G6: 0.01 | H6: =DATE(VALUE(_xlfn.TEXTBEFORE(_xlfn.TEXTAFTER(B6,"""year"": """),"""")),VALUE(_xlfn.TEXTBEFORE(_xlfn.TEXTAFTER(B6,"""month"": """),"""")),VALUE(_xlfn.TEXTBEFORE(_xlfn.TEXTAFTER(B6,"""date"": """),"""")) ) -> 41518 | I6: =_xlfn.XLOOKUP(E6,Product!$A$2:$A$7,Product!$C$2:$C$7) -> 15 | J6: =I6*F6 -> 37470 | K6: =J6*(1-IF(G6="-",0,G6)) -> 37095.3 | L6: =K6-(_xlfn.XLOOKUP(E6,Product!$A$2:$A$7,Product!$B$2:$B$7)*F6) -> 24605.3 | M6: =YEAR(Table1[[#This Row],[Order date]]) -> 2013 | N6: {=_xlfn.IFS(G6=0,"No Discount", ROUND(G6*100,0)<=4,"Low", ROUND(G6*100,0)<=9,"Medium", ROUND(G6*100,0)<=15,"High")} -> Low | O6: =TEXT(Table1[[#This Row],[Order date]],"mmmm") -> September
A7: ="ORD"&"-"&_xlfn.XLOOKUP(C7,Guide!$B$22:$B$26,Guide!$C$22:$C$26)&"-"&_xlfn.XLOOKUP(D7,Guide!$B$29:$B$33,Guide!$C$29:$C$33)&"-"&TEXT(H7,"yyyymmdd") -> ORD-USA-CPR-20130901 | B7: {"type": "buyerDetails", "info": ["origin": "United States of America", "segment": "Channel Partners", "date": "1", "month": "9", "year": "2013", "units": "1989"]} | C7: United States of America | D7: Channel Partners | E7: Amarilla | F7: 1989 | G7: 0.01 | H7: =DATE(VALUE(_xlfn.TEXTBEFORE(_xlfn.TEXTAFTER(B7,"""year"": """),"""")),VALUE(_xlfn.TEXTBEFORE(_xlfn.TEXTAFTER(B7,"""month"": """),"""")),VALUE(_xlfn.TEXTBEFORE(_xlfn.TEXTAFTER(B7,"""date"": """),"""")) ) -> 41518 | I7: =_xlfn.XLOOKUP(E7,Product!$A$2:$A$7,Product!$C$2:$C$7) -> 350 | J7: =I7*F7 -> 696150 | K7: =J7*(1-IF(G7="-",0,G7)) -> 689188.5 | L7: =K7-(_xlfn.XLOOKUP(E7,Product!$A$2:$A$7,Product!$B$2:$B$7)*F7) -> 291388.5 | M7: =YEAR(Table1[[#This Row],[Order date]]) -> 2013 | N7: {=_xlfn.IFS(G7=0,"No Discount", ROUND(G7*100,0)<=4,"Low", ROUND(G7*100,0)<=9,"Medium", ROUND(G7*100,0)<=15,"High")} -> Low | O7: =TEXT(Table1[[#This Row],[Order date]],"mmmm") -> September
A8: ="ORD"&"-"&_xlfn.XLOOKUP(C8,Guide!$B$22:$B$26,Guide!$C$22:$C$26)&"-"&_xlfn.XLOOKUP(D8,Guide!$B$29:$B$33,Guide!$C$29:$C$33)&"-"&TEXT(H8,"yyyymmdd") -> ORD-GER-GOV-20130901 | B8: {"type": "buyerDetails", "info": ["origin": "Germany", "segment": "Government", "date": "1", "month": "9", "year": "2013", "units": "1797"]} | C8: Germany | D8: Government | E8: Montana | F8: 1797 | G8: 0.03 | H8: =DATE(VALUE(_xlfn.TEXTBEFORE(_xlfn.TEXTAFTER(B8,"""year"": """),"""")),VALUE(_xlfn.TEXTBEFORE(_xlfn.TEXTAFTER(B8,"""month"": """),"""")),VALUE(_xlfn.TEXTBEFORE(_xlfn.TEXTAFTER(B8,"""date"": """),"""")) ) -> 41518 | I8: =_xlfn.XLOOKUP(E8,Product!$A$2:$A$7,Product!$C$2:$C$7) -> 15 | J8: =I8*F8 -> 26955 | K8: =J8*(1-IF(G8="-",0,G8)) -> 26146.35 | L8: =K8-(_xlfn.XLOOKUP(E8,Product!$A$2:$A$7,Product!$B$2:$B$7)*F8) -> 17161.35 | M8: =YEAR(Table1[[#This Row],[Order date]]) -> 2013 | N8: {=_xlfn.IFS(G8=0,"No Discount", ROUND(G8*100,0)<=4,"Low", ROUND(G8*100,0)<=9,"Medium", ROUND(G8*100,0)<=15,"High")} -> Low | O8: =TEXT(Table1[[#This Row],[Order date]],"mmmm") -> September
A9: ="ORD"&"-"&_xlfn.XLOOKUP(C9,Guide!$B$22:$B$26,Guide!$C$22:$C$26)&"-"&_xlfn.XLOOKUP(D9,Guide!$B$29:$B$33,Guide!$C$29:$C$33)&"-"&TEXT(H9,"yyyymmdd") -> ORD-MXC-GOV-20130901 | B9: {"type": "buyerDetails", "info": ["origin": "Mexico", "segment": "Government", "date": "1", "month": "9", "year": "2013", "units": "1760"]} | C9: Mexico | D9: Government | E9: Paseo | F9: 1760 | G9: 0.03 | H9: =DATE(VALUE(_xlfn.TEXTBEFORE(_xlfn.TEXTAFTER(B9,"""year"": """),"""")),VALUE(_xlfn.TEXTBEFORE(_xlfn.TEXTAFTER(B9,"""month"": """),"""")),VALUE(_xlfn.TEXTBEFORE(_xlfn.TEXTAFTER(B9,"""date"": """),"""")) ) -> 41518 | I9: =_xlfn.XLOOKUP(E9,Product!$A$2:$A$7,Product!$C$2:$C$7) -> 20 | J9: =I9*F9 -> 35200 | K9: =J9*(1-IF(G9="-",0,G9)) -> 34144 | L9: =K9-(_xlfn.XLOOKUP(E9,Product!$A$2:$A$7,Product!$B$2:$B$7)*F9) -> 16544 | M9: =YEAR(Table1[[#This Row],[Order date]]) -> 2013 | N9: {=_xlfn.IFS(G9=0,"No Discount", ROUND(G9*100,0)<=4,"Low", ROUND(G9*100,0)<=9,"Medium", ROUND(G9*100,0)<=15,"High")} -> Low | O9: =TEXT(Table1[[#This Row],[Order date]],"mmmm") -> September
A10: ="ORD"&"-"&_xlfn.XLOOKUP(C10,Guide!$B$22:$B$26,Guide!$C$22:$C$26)&"-"&_xlfn.XLOOKUP(D10,Guide!$B$29:$B$33,Guide!$C$29:$C$33)&"-"&TEXT(H10,"yyyymmdd") -> ORD-USA-GOV-20130901 | B10: {"type": "buyerDetails", "info": ["origin": "United States of America", "segment": "Government", "date": "1", "month": "9", "year": "2013", "units": "736"]} | C10: United States of America | D10: Government | E10: Velo | F10: 736 | G10: 0.04 | H10: =DATE(VALUE(_xlfn.TEXTBEFORE(_xlfn.TEXTAFTER(B10,"""year"": """),"""")),VALUE(_xlfn.TEXTBEFORE(_xlfn.TEXTAFTER(B10,"""month"": """),"""")),VALUE(_xlfn.TEXTBEFORE(_xlfn.TEXTAFTER(B10,"""date"": """),"""")) ) -> 41518 | I10: =_xlfn.XLOOKUP(E10,Product!$A$2:$A$7,Product!$C$2:$C$7) -> 180 | J10: =I10*F10 -> 132480 | K10: =J10*(1-IF(G10="-",0,G10)) -> 127180.8 | L10: =K10-(_xlfn.XLOOKUP(E10,Product!$A$2:$A$7,Product!$B$2:$B$7)*F10) -> 38860.8 | M10: =YEAR(Table1[[#This Row],[Order date]]) -> 2013 | N10: {=_xlfn.IFS(G10=0,"No Discount", ROUND(G10*100,0)<=4,"Low", ROUND(G10*100,0)<=9,"Medium", ROUND(G10*100,0)<=15,"High")} -> Low | O10: =TEXT(Table1[[#This Row],[Order date]],"mmmm") -> September
A11: ="ORD"&"-"&_xlfn.XLOOKUP(C11,Guide!$B$22:$B$26,Guide!$C$22:$C$26)&"-"&_xlfn.XLOOKUP(D11,Guide!$B$29:$B$33,Guide!$C$29:$C$33)&"-"&TEXT(H11,"yyyymmdd") -> ORD-USA-GOV-20130901 | B11: {"type": "buyerDetails", "info": ["origin": "United States of America", "segment": "Government", "date": "1", "month": "9", "year": "2013", "units": "349"]} | C11: United States of America | D11: Government | E11: VTT | F11: 349 | G11: 0.04 | H11: =DATE(VALUE(_xlfn.TEXTBEFORE(_xlfn.TEXTAFTER(B11,"""year"": """),"""")),VALUE(_xlfn.TEXTBEFORE(_xlfn.TEXTAFTER(B11,"""month"": """),"""")),VALUE(_xlfn.TEXTBEFORE(_xlfn.TEXTAFTER(B11,"""date"": """),"""")) ) -> 41518 | I11: =_xlfn.XLOOKUP(E11,Product!$A$2:$A$7,Product!$C$2:$C$7) -> 300 | J11: =I11*F11 -> 104700 | K11: =J11*(1-IF(G11="-",0,G11)) -> 100512 | L11: =K11-(_xlfn.XLOOKUP(E11,Product!$A$2:$A$7,Product!$B$2:$B$7)*F11) -> 13262 | M11: =YEAR(Table1[[#This Row],[Order date]]) -> 2013 | N11: {=_xlfn.IFS(G11=0,"No Discount", ROUND(G11*100,0)<=4,"Low", ROUND(G11*100,0)<=9,"Medium", ROUND(G11*100,0)<=15,"High")} -> Low | O11: =TEXT(Table1[[#This Row],[Order date]],"mmmm") -> September
A12: ="ORD"&"-"&_xlfn.XLOOKUP(C12,Guide!$B$22:$B$26,Guide!$C$22:$C$26)&"-"&_xlfn.XLOOKUP(D12,Guide!$B$29:$B$33,Guide!$C$29:$C$33)&"-"&TEXT(H12,"yyyymmdd") -> ORD-CND-GOV-20130901 | B12: {"type": "buyerDetails", "info": ["origin": "Canada", "segment": "Government", "date": "1", "month": "9", "year": "2013", "units": "2646"]} | C12: Canada | D12: Government | E12: Velo | F12: 2646 | G12: 0.04 | H12: =DATE(VALUE(_xlfn.TEXTBEFORE(_xlfn.TEXTAFTER(B12,"""year"": """),"""")),VALUE(_xlfn.TEXTBEFORE(_xlfn.TEXTAFTER(B12,"""month"": """),"""")),VALUE(_xlfn.TEXTBEFORE(_xlfn.TEXTAFTER(B12,"""date"": """),"""")) ) -> 41518 | I12: =_xlfn.XLOOKUP(E12,Product!$A$2:$A$7,Product!$C$2:$C$7) -> 180 | J12: =I12*F12 -> 476280 | K12: =J12*(1-IF(G12="-",0,G12)) -> 457228.8 | L12: =K12-(_xlfn.XLOOKUP(E12,Product!$A$2:$A$7,Product!$B$2:$B$7)*F12) -> 139708.8 | M12: =YEAR(Table1[[#This Row],[Order date]]) -> 2013 | N12: {=_xlfn.IFS(G12=0,"No Discount", ROUND(G12*100,0)<=4,"Low", ROUND(G12*100,0)<=9,"Medium", ROUND(G12*100,0)<=15,"High")} -> Low | O12: =TEXT(Table1[[#This Row],[Order date]],"mmmm") -> September
A13: ="ORD"&"-"&_xlfn.XLOOKUP(C13,Guide!$B$22:$B$26,Guide!$C$22:$C$26)&"-"&_xlfn.XLOOKUP(D13,Guide!$B$29:$B$33,Guide!$C$29:$C$33)&"-"&TEXT(H13,"yyyymmdd") -> ORD-CND-GOV-20130901 | B13: {"type": "buyerDetails", "info": ["origin": "Canada", "segment": "Government", "date": "1", "month": "9", "year": "2013", "units": "2349"]} | C13: Canada | D13: Government | E13: Paseo | F13: 2349 | G13: 0.05 | H13: =DATE(VALUE(_xlfn.TEXTBEFORE(_xlfn.TEXTAFTER(B13,"""year"": """),"""")),VALUE(_xlfn.TEXTBEFORE(_xlfn.TEXTAFTER(B13,"""month"": """),"""")),VALUE(_xlfn.TEXTBEFORE(_xlfn.TEXTAFTER(B13,"""date"": """),"""")) ) -> 41518 | I13: =_xlfn.XLOOKUP(E13,Product!$A$2:$A$7,Product!$C$2:$C$7) -> 20 | J13: =I13*F13 -> 46980 | K13: =J13*(1-IF(G13="-",0,G13)) -> 44631 | L13: =K13-(_xlfn.XLOOKUP(E13,Product!$A$2:$A$7,Product!$B$2:$B$7)*F13) -> 21141 | M13: =YEAR(Table1[[#This Row],[Order date]]) -> 2013 | N13: {=_xlfn.IFS(G13=0,"No Discount", ROUND(G13*100,0)<=4,"Low", ROUND(G13*100,0)<=9,"Medium", ROUND(G13*100,0)<=15,"High")} -> Medium | O13: =TEXT(Table1[[#This Row],[Order date]],"mmmm") -> September
... A701: ="ORD"&"-"&_xlfn.XLOOKUP(C701,Guide!$B$22:$B$26,Guide!$C$22:$C$26)&"-"&_xlfn.XLOOKUP(D701,Guide!$B$29:$B$33,Guide!$C$29:$C$33)&"-"&TEXT(H701,"yyyymmdd") -> ORD-USA-CPR-20141201 | B701: {"type": "buyerDetails", "info": ["origin": "United States of America", "segment": "Channel Partners", "date": "1", "month": "12", "year": "2014", "units": "914"]} | C701: United States of America | D701: Channel Partners | E701: Velo | F701: 914 | G701: 0.15 | H701: =DATE(VALUE(_xlfn.TEXTBEFORE(_xlfn.TEXTAFTER(B701,"""year"": """),"""")),VALUE(_xlfn.TEXTBEFORE(_xlfn.TEXTAFTER(B701,"""month"": """),"""")),VALUE(_xlfn.TEXTBEFORE(_xlfn.TEXTAFTER(B701,"""date"": """),"""")) ) -> 41974 | I701: =_xlfn.XLOOKUP(E701,Product!$A$2:$A$7,Product!$C$2:$C$7) -> 180 | J701: =I701*F701 -> 164520 | K701: =J701*(1-IF(G701="-",0,G701)) -> 139842 | L701: =K701-(_xlfn.XLOOKUP(E701,Product!$A$2:$A$7,Product!$B$2:$B$7)*F701) -> 30162 | M701: =YEAR(Table1[[#This Row],[Order date]]) -> 2014 | N701: {=_xlfn.IFS(G701=0,"No Discount", ROUND(G701*100,0)<=4,"Low", ROUND(G701*100,0)<=9,"Medium", ROUND(G701*100,0)<=15,"High")} -> High | O701: =TEXT(Table1[[#This Row],[Order date]],"mmmm") -> December

Sheet Discount
A1: Discount type | B1: Discount range
A2: Low | B2: 1% - 4%
A3: Medium | B3: 5% - 9%
A4: High | B4: 10% - 15%

Sheet Product
A1: Product | B1: Manufacturing cost | C1: Selling price
A2: Carretera | B2: 3 | C2: 20
A3: Montana | B3: 5 | C3: 15
A4: Paseo | B4: 10 | C4: 20
A5: Velo | B5: 120 | C5: 180
A6: VTT | B6: 250 | C6: 300
A7: Amarilla | B7: 200 | C7: 350

Sheet Other financials
A1: Name | B1: Definition | C1: Value | D1: Year | F1: Year | G1: Operating Cost | H1: Net Profit
A2: G&A Cost | B2: General expenses & administrative expenses | C2: 854023 | D2: 2013 | F2: 2013 | G2: {=SUMPRODUCT((YEAR('Order raw'!H2:H701)=2013)*'Order raw'!L2:L701)-C2-C3} -> 4715804.5 | H2: =G2-C4 -> 3678328.5
A3: Handling cost | B3: Cost for handling orders | C3: 2895322 | D3: 2013 | F3: 2014 | G3: {=SUMPRODUCT((YEAR('Order raw'!H2:H701)=2014)*'Order raw'!L2:L701)-C5-C6} -> 16634971 | H3: =G3-C7 -> 12975278
A4: Tax | B4: Taxes charged to the company | C4: 1037476 | D4: 2013
A5: G&A Cost | B5: General expenses & administrative expenses | C5: 3532853 | D5: 2014
A6: Handling cost | B6: Cost for handling orders | C6: 9213451 | D6: 2014
A7: Tax | B7: Taxes charged to the company | C7: 3659693 | D7: 2014
A8: Revenue | B8: Projected revenue | C8: 39582132 | D8: 2015
A9: Net Profit | B9: Projected net profit | C9: 16652123 | D9: 2015

Sheet Pivot
A1: Country origin | B1: Revenue | C1: Gross Profit | E1: Buyer segment | F1: Sum of Revenue | G1: Sum of Gross Profit | I1: Product name | J1: Revenue | K1: Gross Profit | M1: Order date | N1: Revenue | O1: Gross Profit | Q1: Order Year | R1: Sum of Revenue | S1: Sum of Gross Profit | T1: Count of Order ID | V1: Sum of Total Price | W1: Order Year | AA1: Sum of Revenue | AB1: Order Year | AD1: Product | AE1: 2013 | AF1: 2014 | AK1: Sum of Gross Profit | AL1: Order Year
A2: Canada | B2: 28710422 | C2: 7613158.5 | E2: Channel Partners | F2: 21084905 | G2: 5946436.6 | I2: Amarilla | J2: 49984791 | K2: 18922391 | M2: 41518 | N2: 6117183.9 | O2: 1681359 | Q2: 2013 | R2: 31433351 | S2: 8465149.5 | T2: 175 | V2: Product name | W2: 2013 | X2: 2014 | AA2: Product name | AB2: 2013 | AC2: 2014 | AD2: Amarilla | AE2: =IFERROR(GETPIVOTDATA("Sum of Revenue",Pivot!$AA$1,"Product name",AD2,"Order Year",2013),0) -> 10780910 | AF2: =IFERROR(GETPIVOTDATA("Sum of Revenue",Pivot!$AA$1,"Product name",AD2,"Order Year",2014),0) -> 39203881 | AK2: Product name | AL2: 2013 | AM2: 2014
A3: France | B3: 28612739 | C3: 7981388.9 | E3: Enterprise | F3: 19748978 | G3: 5877876.6 | I3: Carretera | J3: 2721137.1 | K3: 2280608.1 | M3: 41548 | N3: 11188754 | O3: 3385490.5 | Q3: 2014 | R3: 1.0375485e+08 | S3: 29381275 | T3: 525 | V3: Amarilla | W3: 11790800 | X3: 42568400 | AA3: Amarilla | AB3: 10780910 | AC3: 39203881 | AD3: Carretera | AE3: =IFERROR(GETPIVOTDATA("Sum of Revenue",Pivot!$AA$1,"Product name",AD3,"Order Year",2013),0) -> 573753.4 | AF3: =IFERROR(GETPIVOTDATA("Sum of Revenue",Pivot!$AA$1,"Product name",AD3,"Order Year",2014),0) -> 2147383.7 | AK3: Amarilla | AL3: 4043310 | AM3: 14879081
A4: Germany | B4: 26042560 | C4: 7638942.5 | E4: Government | F4: 56852365 | G4: 16604030 | I4: Montana | J4: 2153704.9 | K4: 1382729.9 | M4: 41579 | N4: 7630027 | O4: 1680771.9 | Q4: Grand Total | R4: 1.351882e+08 | S4: 37846424 | T4: 700 | V4: Carretera | W4: 628080 | X4: 2308780 | AA4: Carretera | AB4: 573753.4 | AC4: 2147383.7 | AD4: Montana | AE4: =IFERROR(GETPIVOTDATA("Sum of Revenue",Pivot!$AA$1,"Product name",AD4,"Order Year",2013),0) -> 503115.45 | AF4: =IFERROR(GETPIVOTDATA("Sum of Revenue",Pivot!$AA$1,"Product name",AD4,"Order Year",2014),0) -> 1650589.5 | AK4: Carretera | AL4: 479541.4 | AM4: 1801066.7
A5: Mexico | B5: 22895568 | C5: 6626055.7 | E5: Midmarket | F5: 17594853 | G5: 4660742.6 | I5: Paseo | J5: 6282542 | K5: 2900182 | M5: 41609 | N5: 6497387.1 | O5: 1717528 | V5: Montana | W5: 544200 | X5: 1768725 | AA5: Montana | AB5: 503115.45 | AC5: 1650589.5 | AD5: Paseo | AE5: =IFERROR(GETPIVOTDATA("Sum of Revenue",Pivot!$AA$1,"Product name",AD5,"Order Year",2013),0) -> 1531025 | AF5: =IFERROR(GETPIVOTDATA("Sum of Revenue",Pivot!$AA$1,"Product name",AD5,"Order Year",2014),0) -> 4751517 | AK5: Montana | AL5: 321715.45 | AM5: 1061014.5
A6: United States of America | B6: 28926909 | C6: 7986878.4 | E6: Small Business | F6: 19907099 | G6: 4757338.5 | I6: Velo | J6: 27118509 | K6: 7627749.2 | M6: 41640 | N6: 8236148.2 | O6: 2249882.2 | Q6: Revenue | R6: =GETPIVOTDATA("Sum of Revenue",$Q$1) -> 1.351882e+08 | V6: Paseo | W6: 1644940 | X6: 5119780 | AA6: Paseo | AB6: 1531025 | AC6: 4751517 | AD6: Velo | AE6: =IFERROR(GETPIVOTDATA("Sum of Revenue",Pivot!$AA$1,"Product name",AD6,"Order Year",2013),0) -> 6536577.6 | AF6: =IFERROR(GETPIVOTDATA("Sum of Revenue",Pivot!$AA$1,"Product name",AD6,"Order Year",2014),0) -> 20581932 | AK6: Paseo | AL6: 708555 | AM6: 2191627
A7: Revenue by Country | I7: VTT | J7: 46927514 | K7: 4732763.5 | M7: 41671 | N7: 7837279.5 | O7: 2196795.5 | Q7: Gross Profit | R7: =GETPIVOTDATA("Sum of Gross Profit",$Q$1) -> 37846424 | V7: Velo | W7: 7104780 | X7: 22131360 | AA7: Velo | AB7: 6536577.6 | AC7: 20581932 | AD7: VTT | AE7: =IFERROR(GETPIVOTDATA("Sum of Revenue",Pivot!$AA$1,"Product name",AD7,"Order Year",2013),0) -> 11507970 | AF7: =IFERROR(GETPIVOTDATA("Sum of Revenue",Pivot!$AA$1,"Product name",AD7,"Order Year",2014),0) -> 35419544 | AK7: Velo | AL7: 1800057.6 | AM7: 5827691.6
M8: 41699 | N8: 6131979.2 | O8: 1667581.2 | Q8: Total Order | R8: =GETPIVOTDATA("Count of Order ID",$Q$1) -> 700 | V8: VTT | W8: 12475200 | X8: 38158500 | AA8: VTT | AB8: 11507970 | AC8: 35419544 | AK8: VTT | AL8: 1111970 | AM8: 3620793.5
M9: 41730 | N9: 9126710.1 | O9: 2930988.1 | Q9: KPI | AA9: Revenue Growth by Product
A10: Discount Tier | B10: Revenue | C10: Gross Profit | M10: 41760 | N10: 6483235.6 | O10: 1883465.6
A11: No Discount | B11: 12596810 | C11: 4323126 | M11: 41791 | N11: 13302620 | O11: 3689270.4 | V11: Sum of Revenue | W11: Buyer segment
A12: Low | B12: 26821187 | C12: 8240410.7 | M12: 41821 | N12: 7899817.2 | O12: 2348582.2 | V12: Product name | W12: Channel Partners | X12: Enterprise | Y12: Government | Z12: Midmarket | AA12: Small Business | AB12: Product Name | AC12: Channel Partners | AD12: Enterprise | AE12: Government | AF12: Midmarket | AG12: Small Business
A13: Medium | B13: 46478506 | C13: 12803260 | M13: 41852 | N13: 7779475.6 | O13: 2176445.6 | V13: Montana | W13: 327305.7 | X13: 313773.75 | Y13: 888647.02 | Z13: 290239.05 | AA13: 333739.43 | AB13: =V13 -> Montana | AC13: =IFERROR(GETPIVOTDATA("Sum of Revenue",Pivot!$V$11,"Product name",$AB13,"Buyer segment",AC$12),0) -> 327305.7 | AD13: =IFERROR(GETPIVOTDATA("Sum of Revenue",Pivot!$V$11,"Product name",$AB13,"Buyer segment",AD$12),0) -> 313773.75 | AE13: =IFERROR(GETPIVOTDATA("Sum of Revenue",Pivot!$V$11,"Product name",$AB13,"Buyer segment",AE$12),0) -> 888647.02 | AF13: =IFERROR(GETPIVOTDATA("Sum of Revenue",Pivot!$V$11,"Product name",$AB13,"Buyer segment",AF$12),0) -> 290239.05 | AG13: =IFERROR(GETPIVOTDATA("Sum of Revenue",Pivot!$V$11,"Product name",$AB13,"Buyer segment",AG$12),0) -> 333739.43
A14: High | B14: 49291696 | C14: 12479628 | M14: 41883 | N14: 6907868.9 | O14: 2086703.9 | V14: Carretera | W14: 471397.8 | X14: 512563.3 | Y14: 1026735.2 | Z14: 449740 | AA14: 260700.8 | AB14: =V14 -> Carretera | AC14: =IFERROR(GETPIVOTDATA("Sum of Revenue",Pivot!$V$11,"Product name",$AB14,"Buyer segment",AC$12),0) -> 471397.8 | AD14: =IFERROR(GETPIVOTDATA("Sum of Revenue",Pivot!$V$11,"Product name",$AB14,"Buyer segment",AD$12),0) -> 512563.3 | AE14: =IFERROR(GETPIVOTDATA("Sum of Revenue",Pivot!$V$11,"Product name",$AB14,"Buyer segment",AE$12),0) -> 1026735.2 | AF14: =IFERROR(GETPIVOTDATA("Sum of Revenue",Pivot!$V$11,"Product name",$AB14,"Buyer segment",AF$12),0) -> 449740 | AG14: =IFERROR(GETPIVOTDATA("Sum of Revenue",Pivot!$V$11,"Product name",$AB14,"Buyer segment",AG$12),0) -> 260700.8 | AK14: Year | AL14: Sum of Operating Profit | AN14: Year | AO14: Sum of Net Profit
A15: Revenue & Gross Profit by Discount Tier | M15: 41913 | N15: 12611631 | O15: 3258355.2 | V15: Paseo | W15: 757504 | X15: 842857.6 | Y15: 2705307.3 | Z15: 1210305.8 | AA15: 766567.3 | AB15: =V15 -> Paseo | AC15: =IFERROR(GETPIVOTDATA("Sum of Revenue",Pivot!$V$11,"Product name",$AB15,"Buyer segment",AC$12),0) -> 757504 | AD15: =IFERROR(GETPIVOTDATA("Sum of Revenue",Pivot!$V$11,"Product name",$AB15,"Buyer segment",AD$12),0) -> 842857.6 | AE15: =IFERROR(GETPIVOTDATA("Sum of Revenue",Pivot!$V$11,"Product name",$AB15,"Buyer segment",AE$12),0) -> 2705307.3 | AF15: =IFERROR(GETPIVOTDATA("Sum of Revenue",Pivot!$V$11,"Product name",$AB15,"Buyer segment",AF$12),0) -> 1210305.8 | AG15: =IFERROR(GETPIVOTDATA("Sum of Revenue",Pivot!$V$11,"Product name",$AB15,"Buyer segment",AG$12),0) -> 766567.3 | AK15: 2013 | AL15: 4715804.5 | AN15: 2013 | AO15: 3678328.5
M16: 41944 | N16: 6078228 | O16: 1693218.9 | V16: Velo | W16: 2743860.6 | X16: 5156982 | Y16: 12199080 | Z16: 3173890.4 | AA16: 3844696.5 | AB16: =V16 -> Velo | AC16: =IFERROR(GETPIVOTDATA("Sum of Revenue",Pivot!$V$11,"Product name",$AB16,"Buyer segment",AC$12),0) -> 2743860.6 | AD16: =IFERROR(GETPIVOTDATA("Sum of Revenue",Pivot!$V$11,"Product name",$AB16,"Buyer segment",AD$12),0) -> 5156982 | AE16: =IFERROR(GETPIVOTDATA("Sum of Revenue",Pivot!$V$11,"Product name",$AB16,"Buyer segment",AE$12),0) -> 12199080 | AF16: =IFERROR(GETPIVOTDATA("Sum of Revenue",Pivot!$V$11,"Product name",$AB16,"Buyer segment",AF$12),0) -> 3173890.4 | AG16: =IFERROR(GETPIVOTDATA("Sum of Revenue",Pivot!$V$11,"Product name",$AB16,"Buyer segment",AG$12),0) -> 3844696.5 | AK16: 2014 | AL16: 16634971 | AN16: 2014 | AO16: 12975278
M17: 41974 | N17: 11359853 | O17: 3199985.7 | V17: VTT | W17: 7520424 | X17: 5521050 | Y17: 17876272 | Z17: 6668367 | AA17: 9341400 | AB17: =V17 -> VTT | AC17: =IFERROR(GETPIVOTDATA("Sum of Revenue",Pivot!$V$11,"Product name",$AB17,"Buyer segment",AC$12),0) -> 7520424 | AD17: =IFERROR(GETPIVOTDATA("Sum of Revenue",Pivot!$V$11,"Product name",$AB17,"Buyer segment",AD$12),0) -> 5521050 | AE17: =IFERROR(GETPIVOTDATA("Sum of Revenue",Pivot!$V$11,"Product name",$AB17,"Buyer segment",AE$12),0) -> 17876272 | AF17: =IFERROR(GETPIVOTDATA("Sum of Revenue",Pivot!$V$11,"Product name",$AB17,"Buyer segment",AF$12),0) -> 6668367 | AG17: =IFERROR(GETPIVOTDATA("Sum of Revenue",Pivot!$V$11,"Product name",$AB17,"Buyer segment",AG$12),0) -> 9341400
V18: Amarilla | W18: 9264412.5 | X18: 7401751 | Y18: 22156323 | Z18: 5802310.3 | AA18: 5359994.5 | AB18: =V18 -> Amarilla | AC18: =IFERROR(GETPIVOTDATA("Sum of Revenue",Pivot!$V$11,"Product name",$AB18,"Buyer segment",AC$12),0) -> 9264412.5 | AD18: =IFERROR(GETPIVOTDATA("Sum of Revenue",Pivot!$V$11,"Product name",$AB18,"Buyer segment",AD$12),0) -> 7401751 | AE18: =IFERROR(GETPIVOTDATA("Sum of Revenue",Pivot!$V$11,"Product name",$AB18,"Buyer segment",AE$12),0) -> 22156323 | AF18: =IFERROR(GETPIVOTDATA("Sum of Revenue",Pivot!$V$11,"Product name",$AB18,"Buyer segment",AF$12),0) -> 5802310.3 | AG18: =IFERROR(GETPIVOTDATA("Sum of Revenue",Pivot!$V$11,"Product name",$AB18,"Buyer segment",AG$12),0) -> 5359994.5
M20: Year | N20: Gross Profit | O20: G&A Cost | P20: Handling Cost | Q20: Tax | R20: Operating Profit | S20: Net Profit
M21: 2013 | N21: =SUMIFS('Order raw'!$L$2:$L$701,'Order raw'!$M$2:$M$701,M21) -> 8465149.5 | O21: =SUMIFS('Other financials'!$C$2:$C$9,'Other financials'!$A$2:$A$9,"G&A Cost",'Other financials'!$D$2:$D$9,2013) -> 854023 | P21: =SUMIFS('Other financials'!$C$2:$C$9,'Other financials'!$A$2:$A$9,"Handling Cost",'Other financials'!$D$2:$D$9,2013) -> 2895322 | Q21: =SUMIFS('Other financials'!$C$2:$C$9,'Other financials'!$A$2:$A$9,"Tax",'Other financials'!$D$2:$D$9,2013) -> 1037476 | R21: =N21-O21-P21 -> 4715804.5 | S21: =R21-Q21 -> 3678328.5 | U21: =IF(ISNUMBER(IFERROR(GETPIVOTDATA("Sum of Revenue",Pivot!$Q$1,"Order Year",M21),"x")),1) -> 1
M22: 2014 | N22: =SUMIFS('Order raw'!$L$2:$L$701,'Order raw'!$M$2:$M$701,M22) -> 29381275 | O22: =SUMIFS('Other financials'!$C$2:$C$9,'Other financials'!$A$2:$A$9,"G&A Cost",'Other financials'!$D$2:$D$9,2014) -> 3532853 | P22: =SUMIFS('Other financials'!$C$2:$C$9,'Other financials'!$A$2:$A$9,"Handling Cost",'Other financials'!$D$2:$D$9,2014) -> 9213451 | Q22: =SUMIFS('Other financials'!$C$2:$C$9,'Other financials'!$A$2:$A$9,"Tax",'Other financials'!$D$2:$D$9,2014) -> 3659693 | R22: =N22-O22-P22 -> 16634971 | S22: =R22-Q22 -> 12975278 | U22: =IF(ISNUMBER(IFERROR(GETPIVOTDATA("Sum of Revenue",Pivot!$Q$1,"Order Year",M22),"x")),1) -> 1
M23: Profitability Breakdown by Year | U23: =IFERROR(GETPIVOTDATA("Sum of Gross Profit",$Q$1,"Order Year",M21),0)*S21/N21+IFERROR(GETPIVOTDATA("Sum of Gross Profit",$Q$1,"Order Year",M22),0)*S22/N22 -> 16653606
A26: Top Product
A27: Product | B27: Revenue | C27: Rank value | E27: Rank | F27: Name | G27: Revenue | H27: Bar
A28: Amarilla | B28: =IFERROR(GETPIVOTDATA("Revenue",$I$1,"Product name",A28),0) -> 49984791 | C28: =B28+ROW()/1000000 -> 49984791 | E28: 1 | F28: =IF(G28=0,"-",INDEX($A$28:$A$33,MATCH(LARGE($C$28:$C$33,E28),$C$28:$C$33,0))) -> Amarilla | G28: =INDEX($B$28:$B$33,MATCH(LARGE($C$28:$C$33,E28),$C$28:$C$33,0)) -> 49984791 | H28: =IF(G28=0,"",REPT("█",MAX(1,ROUND(G28/$G$28*20,0)))) -> ████████████████████
A29: Carretera | B29: =IFERROR(GETPIVOTDATA("Revenue",$I$1,"Product name",A29),0) -> 2721137.1 | C29: =B29+ROW()/1000000 -> 2721137.1 | E29: 2 | F29: =IF(G29=0,"-",INDEX($A$28:$A$33,MATCH(LARGE($C$28:$C$33,E29),$C$28:$C$33,0))) -> VTT | G29: =INDEX($B$28:$B$33,MATCH(LARGE($C$28:$C$33,E29),$C$28:$C$33,0)) -> 46927514 | H29: =IF(G29=0,"",REPT("█",MAX(1,ROUND(G29/$G$28*20,0)))) -> ███████████████████
A30: Montana | B30: =IFERROR(GETPIVOTDATA("Revenue",$I$1,"Product name",A30),0) -> 2153704.9 | C30: =B30+ROW()/1000000 -> 2153705 | E30: 3 | F30: =IF(G30=0,"-",INDEX($A$28:$A$33,MATCH(LARGE($C$28:$C$33,E30),$C$28:$C$33,0))) -> Velo | G30: =INDEX($B$28:$B$33,MATCH(LARGE($C$28:$C$33,E30),$C$28:$C$33,0)) -> 27118509 | H30: =IF(G30=0,"",REPT("█",MAX(1,ROUND(G30/$G$28*20,0)))) -> ███████████
A31: Paseo | B31: =IFERROR(GETPIVOTDATA("Revenue",$I$1,"Product name",A31),0) -> 6282542 | C31: =B31+ROW()/1000000 -> 6282542
A32: Velo | B32: =IFERROR(GETPIVOTDATA("Revenue",$I$1,"Product name",A32),0) -> 27118509 | C32: =B32+ROW()/1000000 -> 27118509
A33: VTT | B33: =IFERROR(GETPIVOTDATA("Revenue",$I$1,"Product name",A33),0) -> 46927514 | C33: =B33+ROW()/1000000 -> 46927514
A43: Top Segment
A44: Segment | B44: Revenue | C44: Rank value | E44: Rank | F44: Name | G44: Revenue | H44: Bar
A45: Channel Partners | B45: =IFERROR(GETPIVOTDATA("Sum of Revenue",$E$1,"Buyer segment",A45),0) -> 21084905 | C45: =B45+ROW()/1000000 -> 21084905 | E45: 1 | F45: =IF(G45=0,"-",INDEX($A$45:$A$49,MATCH(LARGE($C$45:$C$49,E45),$C$45:$C$49,0))) -> Government | G45: =INDEX($B$45:$B$49,MATCH(LARGE($C$45:$C$49,E45),$C$45:$C$49,0)) -> 56852365 | H45: =IF(G45=0,"",REPT("█",MAX(1,ROUND(G45/$G$45*20,0)))) -> ████████████████████
A46: Enterprise | B46: =IFERROR(GETPIVOTDATA("Sum of Revenue",$E$1,"Buyer segment",A46),0) -> 19748978 | C46: =B46+ROW()/1000000 -> 19748978 | E46: 2 | F46: =IF(G46=0,"-",INDEX($A$45:$A$49,MATCH(LARGE($C$45:$C$49,E46),$C$45:$C$49,0))) -> Channel Partners | G46: =INDEX($B$45:$B$49,MATCH(LARGE($C$45:$C$49,E46),$C$45:$C$49,0)) -> 21084905 | H46: =IF(G46=0,"",REPT("█",MAX(1,ROUND(G46/$G$45*20,0)))) -> ███████
A47: Government | B47: =IFERROR(GETPIVOTDATA("Sum of Revenue",$E$1,"Buyer segment",A47),0) -> 56852365 | C47: =B47+ROW()/1000000 -> 56852365 | E47: 3 | F47: =IF(G47=0,"-",INDEX($A$45:$A$49,MATCH(LARGE($C$45:$C$49,E47),$C$45:$C$49,0))) -> Small Business | G47: =INDEX($B$45:$B$49,MATCH(LARGE($C$45:$C$49,E47),$C$45:$C$49,0)) -> 19907099 | H47: =IF(G47=0,"",REPT("█",MAX(1,ROUND(G47/$G$45*20,0)))) -> ███████
A48: Midmarket | B48: =IFERROR(GETPIVOTDATA("Sum of Revenue",$E$1,"Buyer segment",A48),0) -> 17594853 | C48: =B48+ROW()/1000000 -> 17594853
A49: Small Business | B49: =IFERROR(GETPIVOTDATA("Sum of Revenue",$E$1,"Buyer segment",A49),0) -> 19907099 | C49: =B49+ROW()/1000000 -> 19907099

Sheet Dashboard
